{"type":"Dialog","props":{"width":750,"runtime":"infoLog","height":200},"child":[{"type":"Image","props":{"y":0,"x":0,"width":750,"skin":"settingLog/inputInfLog.png","sizeGrid":"29,0,28,0","height":200}},{"type":"Label","props":{"y":100,"x":358,"width":360,"var":"infoText","text":"信息信息信息信息","pivotY":15,"pivotX":180,"height":30,"fontSize":30,"font":"Microsoft YaHei","color":"#56361f","align":"center"}},{"type":"Image","props":{"y":23,"x":480,"var":"roleImg","skin":"storeItem/icon_food_03.png","scaleY":0.8,"scaleX":0.8}}]}